{
  "$schema": "https://wails.io/schemas/config.v2.json",
  "name": "HeadofMasterCEMO",
  "outputfilename": "HeadofMasterCEMO",
  "frontend:install": "npm install",
  "frontend:build": "npm run build",
  "frontend:dev:watcher": "npm run dev",
  "frontend:dev:serverUrl": "auto",
  "author": {
    "name": "BCS",
    "email": "cemsume@neredekal.com"
  },
  "info": {
    "companyName": "BCS",
    "productName": "Head of Master CEMO",
    "productVersion": "0.0.13",
    "copyright": "Copyright © 2024",
    "comments": "Head of Master CEMO"
  }
}